odoo/addons/purchase_stock_cost_update/README.rst
odoo/addons/purchase_stock_cost_update/__init__.py
odoo/addons/purchase_stock_cost_update/__manifest__.py
odoo/addons/purchase_stock_cost_update/i18n/es.po
odoo/addons/purchase_stock_cost_update/i18n/purchase_stock_cost_update.pot
odoo/addons/purchase_stock_cost_update/models/__init__.py
odoo/addons/purchase_stock_cost_update/models/purchase_order.py
odoo/addons/purchase_stock_cost_update/models/stock_valuation_layer.py
odoo/addons/purchase_stock_cost_update/readme/CONFIGURE.md
odoo/addons/purchase_stock_cost_update/readme/CONTEXT.md
odoo/addons/purchase_stock_cost_update/readme/CONTRIBUTORS.md
odoo/addons/purchase_stock_cost_update/readme/DESCRIPTION.md
odoo/addons/purchase_stock_cost_update/readme/ROADMAP.md
odoo/addons/purchase_stock_cost_update/readme/USAGE.md
odoo/addons/purchase_stock_cost_update/static/description/icon.png
odoo/addons/purchase_stock_cost_update/static/description/index.html
odoo/addons/purchase_stock_cost_update/tests/__init__.py
odoo/addons/purchase_stock_cost_update/tests/test_purchase_stock_cost_update.py
odoo/addons/purchase_stock_cost_update/views/purchase_order_form_views.xml
odoo/addons/purchase_stock_cost_update/views/stock_valuation_layer_views.xml
odoo_addon_purchase_stock_cost_update-16.0.1.0.1.dist-info/METADATA
odoo_addon_purchase_stock_cost_update-16.0.1.0.1.dist-info/WHEEL
odoo_addon_purchase_stock_cost_update-16.0.1.0.1.dist-info/top_level.txt
odoo_addon_purchase_stock_cost_update-16.0.1.0.1.dist-info/RECORD
