Metadata-Version: 2.1
Name: odoo-addon-purchase_stock_cost_update
Version: 16.0.1.0.1
Summary: Allows to update valuation layers once the purchase is received
Home-page: https://github.com/OCA/purchase-workflow
Author: Moduon, Odoo Community Association (OCA)
Author-email: support@odoo-community.org
License: LGPL-3
Classifier: Programming Language :: Python
Classifier: Framework :: Odoo
Classifier: Framework :: Odoo :: 16.0
Classifier: License :: OSI Approved :: GNU Lesser General Public License v3 (LGPLv3)
Requires-Python: >=3.10
Requires-Dist: odoo<16.1dev,>=16.0a
